releasemaker/__init__.py
releasemaker/metadata.py
releasemaker/releasemaker.py
releasemaker-0.4.1.data/scripts/releasemaker
releasemaker-0.4.1.dist-info/DESCRIPTION.rst
releasemaker-0.4.1.dist-info/METADATA
releasemaker-0.4.1.dist-info/RECORD
releasemaker-0.4.1.dist-info/WHEEL
releasemaker-0.4.1.dist-info/metadata.json
releasemaker-0.4.1.dist-info/top_level.txt
