Metadata-Version: 2.0
Name: releasemaker
Version: 0.4.1
Summary: Build tool to create releases in GitHub.
Home-page: http://lionheartsw.com/
Author: Dan Loewenherz
Author-email: dan@lionheartsw.com
License: Apache 2.0
Platform: UNKNOWN
